pgque/__init__.py
pgque/async_queue.py
pgque/base.py
pgque/models.py
pgque/py.typed
pgque/sync_queue.py
pgque/workers.py
pgque-0.1.0.dist-info/METADATA
pgque-0.1.0.dist-info/WHEEL
pgque-0.1.0.dist-info/RECORD
