Metadata-Version: 2.4
Name: pgque
Version: 0.1.0
Summary: Add your description here
Author-email: Jannchie <jannchie@gmail.com>
Requires-Python: >=3.12
Requires-Dist: sqlalchemy>=2.0.41
Provides-Extra: async
Requires-Dist: asyncpg>=0.29.0; extra == 'async'
Provides-Extra: psycopg2
Requires-Dist: psycopg2-binary>=2.9.9; extra == 'psycopg2'
Provides-Extra: psycopg3
Requires-Dist: psycopg[binary]>=3.2.9; extra == 'psycopg3'
